scenegen/__init__.py
scenegen/console.py
scenegen/py.typed
scenegen/scene.py
scenegen/shapes.py
scenegen/testscene.py
scenegen/walk.py
scenegen-0.1.2.dist-info/entry_points.txt
scenegen-0.1.2.dist-info/LICENSE.txt
scenegen-0.1.2.dist-info/WHEEL
scenegen-0.1.2.dist-info/METADATA
scenegen-0.1.2.dist-info/RECORD
