Metadata-Version: 2.1
Name: scenegen
Version: 0.1.2
Summary: A scene generator
Home-page: https://gitlab.com/kahara/python-scenegen
License: MIT
Author: Joni Kähärä
Author-email: joni.kahara@async.fi
Requires-Python: >=3.7,<4.0
Classifier: License :: OSI Approved :: MIT License
Classifier: Programming Language :: Python :: 3
Classifier: Programming Language :: Python :: 3.7
Classifier: Programming Language :: Python :: 3.8
Requires-Dist: click (>=7.1.1,<8.0.0)
Requires-Dist: pillow (>=7.0.0,<8.0.0)
